pybotchi_files/__init__.py
pybotchi_files/utils.py
pybotchi_files-0.2.1.dist-info/METADATA
pybotchi_files-0.2.1.dist-info/WHEEL
pybotchi_files-0.2.1.dist-info/RECORD
